complexity_science/__init__.py
complexity_science/test_import.py
complexity_science/ca/__init__.py
complexity_science/ca/models1d.py
complexity_science/ca/models2d.py
complexity_science/ca/models_multi_ca.py
complexity_science/ca/models_network.py
complexity_science/ca/network.py
complexity_science/ca/steady_state.py
complexity_science/ca/test.py
complexity_science/ca/ca/__init__.py
complexity_science/ca/ca/ca1d.py
complexity_science/ca/ca/ca2d.py
complexity_science/ca/ca/ca3d.py
complexity_science/ca/ca/ca_network.py
complexity_science/ca/ca/data_collector.py
complexity_science/ca/ca/multi_ca.py
complexity_science/ca/ca/rule_manager.py
complexity_science/ca/rules1d/__init__.py
complexity_science/ca/rules1d/granular_shake.py
complexity_science/ca/rules1d/thermometer.py
complexity_science/ca/rules1d/wolfram.py
complexity_science/ca/rules2d/__init__.py
complexity_science/ca/rules2d/applause.py
complexity_science/ca/rules2d/brians.py
complexity_science/ca/rules2d/forest_fire.py
complexity_science/ca/rules2d/game_of_life.py
complexity_science/ca/rules2d/mpa.py
complexity_science/ca/rules_network/SIR.py
complexity_science/ca/rules_network/__init__.py
complexity_science/ca/rules_network/brians.py
complexity_science/ca/rules_network/gillespie.py
complexity_science/ca/rules_network/migration.py
complexity_science-0.0.6.dist-info/LICENSE
complexity_science-0.0.6.dist-info/METADATA
complexity_science-0.0.6.dist-info/WHEEL
complexity_science-0.0.6.dist-info/top_level.txt
complexity_science-0.0.6.dist-info/RECORD
