Metadata-Version: 2.1
Name: complexity-science
Version: 0.0.6
Summary: A package for complexity science research
Home-page: https://github.com/complexity-science
Author: Krister Jazz Urog
Author-email: kristerjazz.urog@gmail.com
License: UNKNOWN
Platform: UNKNOWN
Classifier: Programming Language :: Python :: 3
Classifier: License :: OSI Approved :: BSD License
Classifier: Operating System :: OS Independent
Requires-Python: >3.6
Requires-Dist: numpy
Requires-Dist: matplotlib
Requires-Dist: pandas
